{
  "merge_commit_sha": "60dfdb3ee782a24db58756e5ea9c532af76b7b9a",
  "authors": [
    {
      "n": "Denis A. Engemann",
      "e": null
    }
  ],
  "changes": {
    "doc/source/python_reference.rst": {
      "a": 1,
      "d": 0
    },
    "examples/stats/plot_cluster_stats_spatio_temporal_repeated_measures_anova.py": {
      "a": 5,
      "d": 5
    },
    "examples/stats/plot_cluster_stats_time_frequency_repeated_measures_anova.py": {
      "a": 6,
      "d": 6
    },
    "mne/stats/__init__.py": {
      "a": 2,
      "d": 1
    },
    "mne/stats/parametric.py": {
      "a": 107,
      "d": 38
    },
    "mne/stats/tests/test_parametric.py": {
      "a": 63,
      "d": 40
    }
  }
}